{
  "metadata": {
    "timestamp_utc": "2026-02-08T17:10:24.395039+00:00",
    "planned_snapshots": 4,
    "executed_snapshots": 4,
    "snapshot_interval_minutes": 10.0,
    "sleep_between_snapshots_seconds": 0.0,
    "sizes": [
      1400,
      2048
    ],
    "kernels": [
      "auto_t3_controlled",
      "auto_t5_guarded"
    ],
    "sessions": 2,
    "iterations": 10,
    "seed": 2610,
    "pressure": {
      "size": 896,
      "iterations": 3,
      "pulses_per_snapshot": 3
    },
    "t5_policy_path": "research/breakthrough_lab/t5_reliability_abft/policy_hardening_week10_block1_3.json",
    "baseline_block6_path": "research/breakthrough_lab/platform_compatibility/week10_block1_4_long_window_20260208_165345.json",
    "rollback_script_path": "research/breakthrough_lab/platform_compatibility/week9_block5_rusticl_rollback.sh",
    "rollback_sla_path": "research/breakthrough_lab/preprod_signoff/WEEK9_BLOCK6_ROLLBACK_SLA.md",
    "auto_rollback_enabled": true,
    "rollback_after_consecutive_soft_overhead_violations": 3
  },
  "snapshots": [
    {
      "snapshot": 1,
      "pressure": {
        "snapshot": 1,
        "requested": 3,
        "completed": 3,
        "failures": 0,
        "errors": []
      },
      "runs": [
        {
          "status": "ok",
          "returncode": 0,
          "platform_selector": "Clover",
          "kernel": "auto_t3_controlled",
          "size": 1400,
          "seed": 5010,
          "metrics": {
            "platform": "Clover",
            "device": "AMD Radeon RX 590 GME (radeonsi, polaris10, ACO, DRM 3.61, 6.14.0-37-generic)",
            "peak_mean_gflops": 902.514286702161,
            "avg_mean_gflops": 882.110541576449,
            "p95_time_ms": 6.107363200680993,
            "max_error_max": 0.000335693359375,
            "t3_fallback_rate": 0.0,
            "t3_policy_disabled": false
          },
          "snapshot": 1
        },
        {
          "status": "ok",
          "returncode": 0,
          "platform_selector": "Clover",
          "kernel": "auto_t3_controlled",
          "size": 2048,
          "seed": 5658,
          "metrics": {
            "platform": "Clover",
            "device": "AMD Radeon RX 590 GME (radeonsi, polaris10, ACO, DRM 3.61, 6.14.0-37-generic)",
            "peak_mean_gflops": 775.7337529068676,
            "avg_mean_gflops": 772.2442422736601,
            "p95_time_ms": 22.14883344995542,
            "max_error_max": 0.00048828125,
            "t3_fallback_rate": 0.0,
            "t3_policy_disabled": false
          },
          "snapshot": 1
        },
        {
          "status": "ok",
          "returncode": 0,
          "platform_selector": "Clover",
          "kernel": "auto_t5_guarded",
          "size": 1400,
          "seed": 5010,
          "metrics": {
            "platform": "Clover",
            "device": "AMD Radeon RX 590 GME (radeonsi, polaris10, ACO, DRM 3.61, 6.14.0-37-generic)",
            "peak_mean_gflops": 920.0366177279946,
            "avg_mean_gflops": 907.6401013710683,
            "p95_time_ms": 5.967696349489415,
            "max_error_max": 0.000335693359375,
            "t5_overhead_percent": 1.1883291079490017,
            "t5_false_positive_rate": 0.0,
            "t5_disable_events": 0,
            "t5_disable_reason": null
          },
          "snapshot": 1
        },
        {
          "status": "ok",
          "returncode": 0,
          "platform_selector": "Clover",
          "kernel": "auto_t5_guarded",
          "size": 2048,
          "seed": 5658,
          "metrics": {
            "platform": "Clover",
            "device": "AMD Radeon RX 590 GME (radeonsi, polaris10, ACO, DRM 3.61, 6.14.0-37-generic)",
            "peak_mean_gflops": 781.4818164860301,
            "avg_mean_gflops": 776.176017982146,
            "p95_time_ms": 22.00527834975219,
            "max_error_max": 0.00048828125,
            "t5_overhead_percent": 0.5391262322163354,
            "t5_false_positive_rate": 0.0,
            "t5_disable_events": 0,
            "t5_disable_reason": null
          },
          "snapshot": 1
        }
      ],
      "evaluation": {
        "checks": {
          "all_runs_success": {
            "pass": true
          },
          "pressure_failures_zero": {
            "observed": 0,
            "required": 0,
            "pass": true
          },
          "correctness_bound_all_runs": {
            "observed_max": 0.00048828125,
            "required_max": 0.001,
            "pass": true
          },
          "t3_guardrails_all_runs": {
            "observed_fallback_max": 0.0,
            "observed_policy_disabled_total": 0,
            "pass": true
          },
          "t5_guardrails_hard": {
            "observed_disable_total": 0,
            "observed_fp_max": 0.0,
            "observed_overhead_max": 1.1883291079490017,
            "soft_limit_percent": 3.0,
            "hard_limit_percent": 5.0,
            "pass": true
          },
          "t5_overhead_soft_limit": {
            "observed_overhead_max": 1.1883291079490017,
            "required_max": 3.0,
            "pass": true
          },
          "no_regression_vs_block6_clover": {
            "pass": true
          }
        },
        "failed_checks": [],
        "hard_failed_checks": [],
        "soft_overhead_violation": false,
        "decision": "continue",
        "regression_rows": [
          {
            "kernel": "auto_t3_controlled",
            "size": 1400,
            "throughput_delta_percent": 0.8251439764198658,
            "p95_delta_percent": -0.412633836809725
          },
          {
            "kernel": "auto_t3_controlled",
            "size": 2048,
            "throughput_delta_percent": -0.03040651497992929,
            "p95_delta_percent": -0.1891311299184353
          },
          {
            "kernel": "auto_t5_guarded",
            "size": 1400,
            "throughput_delta_percent": -0.18995880581432184,
            "p95_delta_percent": -0.29935078757497696
          },
          {
            "kernel": "auto_t5_guarded",
            "size": 2048,
            "throughput_delta_percent": -0.2280936354977571,
            "p95_delta_percent": 0.08525680821244408
          }
        ],
        "soft_overhead_streak": 0
      }
    },
    {
      "snapshot": 2,
      "pressure": {
        "snapshot": 2,
        "requested": 3,
        "completed": 3,
        "failures": 0,
        "errors": []
      },
      "runs": [
        {
          "status": "ok",
          "returncode": 0,
          "platform_selector": "Clover",
          "kernel": "auto_t3_controlled",
          "size": 1400,
          "seed": 6010,
          "metrics": {
            "platform": "Clover",
            "device": "AMD Radeon RX 590 GME (radeonsi, polaris10, ACO, DRM 3.61, 6.14.0-37-generic)",
            "peak_mean_gflops": 904.5440808209981,
            "avg_mean_gflops": 880.1362681314855,
            "p95_time_ms": 6.1243212997851515,
            "max_error_max": 0.000335693359375,
            "t3_fallback_rate": 0.0,
            "t3_policy_disabled": false
          },
          "snapshot": 2
        },
        {
          "status": "ok",
          "returncode": 0,
          "platform_selector": "Clover",
          "kernel": "auto_t3_controlled",
          "size": 2048,
          "seed": 6658,
          "metrics": {
            "platform": "Clover",
            "device": "AMD Radeon RX 590 GME (radeonsi, polaris10, ACO, DRM 3.61, 6.14.0-37-generic)",
            "peak_mean_gflops": 776.314089583971,
            "avg_mean_gflops": 771.3104908261703,
            "p95_time_ms": 22.14926699953139,
            "max_error_max": 0.0005035400390625,
            "t3_fallback_rate": 0.0,
            "t3_policy_disabled": false
          },
          "snapshot": 2
        },
        {
          "status": "ok",
          "returncode": 0,
          "platform_selector": "Clover",
          "kernel": "auto_t5_guarded",
          "size": 1400,
          "seed": 6010,
          "metrics": {
            "platform": "Clover",
            "device": "AMD Radeon RX 590 GME (radeonsi, polaris10, ACO, DRM 3.61, 6.14.0-37-generic)",
            "peak_mean_gflops": 914.4301929182327,
            "avg_mean_gflops": 905.1384547252412,
            "p95_time_ms": 6.002922700099589,
            "max_error_max": 0.000335693359375,
            "t5_overhead_percent": 1.1245681042207534,
            "t5_false_positive_rate": 0.0,
            "t5_disable_events": 0,
            "t5_disable_reason": null
          },
          "snapshot": 2
        },
        {
          "status": "ok",
          "returncode": 0,
          "platform_selector": "Clover",
          "kernel": "auto_t5_guarded",
          "size": 2048,
          "seed": 6658,
          "metrics": {
            "platform": "Clover",
            "device": "AMD Radeon RX 590 GME (radeonsi, polaris10, ACO, DRM 3.61, 6.14.0-37-generic)",
            "peak_mean_gflops": 782.198977200597,
            "avg_mean_gflops": 777.2321488138107,
            "p95_time_ms": 21.96612349998759,
            "max_error_max": 0.00048828125,
            "t5_overhead_percent": 0.5277041447846018,
            "t5_false_positive_rate": 0.0,
            "t5_disable_events": 0,
            "t5_disable_reason": null
          },
          "snapshot": 2
        }
      ],
      "evaluation": {
        "checks": {
          "all_runs_success": {
            "pass": true
          },
          "pressure_failures_zero": {
            "observed": 0,
            "required": 0,
            "pass": true
          },
          "correctness_bound_all_runs": {
            "observed_max": 0.0005035400390625,
            "required_max": 0.001,
            "pass": true
          },
          "t3_guardrails_all_runs": {
            "observed_fallback_max": 0.0,
            "observed_policy_disabled_total": 0,
            "pass": true
          },
          "t5_guardrails_hard": {
            "observed_disable_total": 0,
            "observed_fp_max": 0.0,
            "observed_overhead_max": 1.1245681042207534,
            "soft_limit_percent": 3.0,
            "hard_limit_percent": 5.0,
            "pass": true
          },
          "t5_overhead_soft_limit": {
            "observed_overhead_max": 1.1245681042207534,
            "required_max": 3.0,
            "pass": true
          },
          "no_regression_vs_block6_clover": {
            "pass": true
          }
        },
        "failed_checks": [],
        "hard_failed_checks": [],
        "soft_overhead_violation": false,
        "decision": "continue",
        "regression_rows": [
          {
            "kernel": "auto_t3_controlled",
            "size": 1400,
            "throughput_delta_percent": 0.5994847251637511,
            "p95_delta_percent": -0.13611312411833157
          },
          {
            "kernel": "auto_t3_controlled",
            "size": 2048,
            "throughput_delta_percent": -0.1512837549924603,
            "p95_delta_percent": -0.18717739452311866
          },
          {
            "kernel": "auto_t5_guarded",
            "size": 1400,
            "throughput_delta_percent": -0.4650562308797461,
            "p95_delta_percent": 0.28916609055326326
          },
          {
            "kernel": "auto_t5_guarded",
            "size": 2048,
            "throughput_delta_percent": -0.09233552908338016,
            "p95_delta_percent": -0.09282879160097943
          }
        ],
        "soft_overhead_streak": 0
      }
    },
    {
      "snapshot": 3,
      "pressure": {
        "snapshot": 3,
        "requested": 3,
        "completed": 3,
        "failures": 0,
        "errors": []
      },
      "runs": [
        {
          "status": "ok",
          "returncode": 0,
          "platform_selector": "Clover",
          "kernel": "auto_t3_controlled",
          "size": 1400,
          "seed": 7010,
          "metrics": {
            "platform": "Clover",
            "device": "AMD Radeon RX 590 GME (radeonsi, polaris10, ACO, DRM 3.61, 6.14.0-37-generic)",
            "peak_mean_gflops": 899.523818446503,
            "avg_mean_gflops": 884.3712457172705,
            "p95_time_ms": 6.162586850177831,
            "max_error_max": 0.0002899169921875,
            "t3_fallback_rate": 0.0,
            "t3_policy_disabled": false
          },
          "snapshot": 3
        },
        {
          "status": "ok",
          "returncode": 0,
          "platform_selector": "Clover",
          "kernel": "auto_t3_controlled",
          "size": 2048,
          "seed": 7658,
          "metrics": {
            "platform": "Clover",
            "device": "AMD Radeon RX 590 GME (radeonsi, polaris10, ACO, DRM 3.61, 6.14.0-37-generic)",
            "peak_mean_gflops": 774.4109824945529,
            "avg_mean_gflops": 770.7606068520714,
            "p95_time_ms": 22.204869900315316,
            "max_error_max": 0.000579833984375,
            "t3_fallback_rate": 0.0,
            "t3_policy_disabled": false
          },
          "snapshot": 3
        },
        {
          "status": "ok",
          "returncode": 0,
          "platform_selector": "Clover",
          "kernel": "auto_t5_guarded",
          "size": 1400,
          "seed": 7010,
          "metrics": {
            "platform": "Clover",
            "device": "AMD Radeon RX 590 GME (radeonsi, polaris10, ACO, DRM 3.61, 6.14.0-37-generic)",
            "peak_mean_gflops": 917.2692935421951,
            "avg_mean_gflops": 898.8232798002334,
            "p95_time_ms": 5.996161849543569,
            "max_error_max": 0.0002899169921875,
            "t5_overhead_percent": 1.2053005048759495,
            "t5_false_positive_rate": 0.0,
            "t5_disable_events": 0,
            "t5_disable_reason": null
          },
          "snapshot": 3
        },
        {
          "status": "ok",
          "returncode": 0,
          "platform_selector": "Clover",
          "kernel": "auto_t5_guarded",
          "size": 2048,
          "seed": 7658,
          "metrics": {
            "platform": "Clover",
            "device": "AMD Radeon RX 590 GME (radeonsi, polaris10, ACO, DRM 3.61, 6.14.0-37-generic)",
            "peak_mean_gflops": 781.7289685383374,
            "avg_mean_gflops": 777.1847551178129,
            "p95_time_ms": 21.992245749652284,
            "max_error_max": 0.00048828125,
            "t5_overhead_percent": 0.5298428635343416,
            "t5_false_positive_rate": 0.0,
            "t5_disable_events": 0,
            "t5_disable_reason": null
          },
          "snapshot": 3
        }
      ],
      "evaluation": {
        "checks": {
          "all_runs_success": {
            "pass": true
          },
          "pressure_failures_zero": {
            "observed": 0,
            "required": 0,
            "pass": true
          },
          "correctness_bound_all_runs": {
            "observed_max": 0.000579833984375,
            "required_max": 0.001,
            "pass": true
          },
          "t3_guardrails_all_runs": {
            "observed_fallback_max": 0.0,
            "observed_policy_disabled_total": 0,
            "pass": true
          },
          "t5_guardrails_hard": {
            "observed_disable_total": 0,
            "observed_fp_max": 0.0,
            "observed_overhead_max": 1.2053005048759495,
            "soft_limit_percent": 3.0,
            "hard_limit_percent": 5.0,
            "pass": true
          },
          "t5_overhead_soft_limit": {
            "observed_overhead_max": 1.2053005048759495,
            "required_max": 3.0,
            "pass": true
          },
          "no_regression_vs_block6_clover": {
            "pass": true
          }
        },
        "failed_checks": [],
        "hard_failed_checks": [],
        "soft_overhead_violation": false,
        "decision": "continue",
        "regression_rows": [
          {
            "kernel": "auto_t3_controlled",
            "size": 1400,
            "throughput_delta_percent": 1.0835422266879873,
            "p95_delta_percent": 0.4878493377779751
          },
          {
            "kernel": "auto_t3_controlled",
            "size": 2048,
            "throughput_delta_percent": -0.22246806993502502,
            "p95_delta_percent": 0.06338992548856309
          },
          {
            "kernel": "auto_t5_guarded",
            "size": 1400,
            "throughput_delta_percent": -1.1595141646591893,
            "p95_delta_percent": 0.17621443380198332
          },
          {
            "kernel": "auto_t5_guarded",
            "size": 2048,
            "throughput_delta_percent": -0.09842765160431863,
            "p95_delta_percent": 0.025981433134427967
          }
        ],
        "soft_overhead_streak": 0
      }
    },
    {
      "snapshot": 4,
      "pressure": {
        "snapshot": 4,
        "requested": 3,
        "completed": 3,
        "failures": 0,
        "errors": []
      },
      "runs": [
        {
          "status": "ok",
          "returncode": 0,
          "platform_selector": "Clover",
          "kernel": "auto_t3_controlled",
          "size": 1400,
          "seed": 8010,
          "metrics": {
            "platform": "Clover",
            "device": "AMD Radeon RX 590 GME (radeonsi, polaris10, ACO, DRM 3.61, 6.14.0-37-generic)",
            "peak_mean_gflops": 903.5073225613546,
            "avg_mean_gflops": 882.1237006860633,
            "p95_time_ms": 6.075018699903012,
            "max_error_max": 0.00029754638671875,
            "t3_fallback_rate": 0.0,
            "t3_policy_disabled": false
          },
          "snapshot": 4
        },
        {
          "status": "ok",
          "returncode": 0,
          "platform_selector": "Clover",
          "kernel": "auto_t3_controlled",
          "size": 2048,
          "seed": 8658,
          "metrics": {
            "platform": "Clover",
            "device": "AMD Radeon RX 590 GME (radeonsi, polaris10, ACO, DRM 3.61, 6.14.0-37-generic)",
            "peak_mean_gflops": 774.6460671621267,
            "avg_mean_gflops": 771.0135509284464,
            "p95_time_ms": 22.20921195007577,
            "max_error_max": 0.000579833984375,
            "t3_fallback_rate": 0.0,
            "t3_policy_disabled": false
          },
          "snapshot": 4
        },
        {
          "status": "ok",
          "returncode": 0,
          "platform_selector": "Clover",
          "kernel": "auto_t5_guarded",
          "size": 1400,
          "seed": 8010,
          "metrics": {
            "platform": "Clover",
            "device": "AMD Radeon RX 590 GME (radeonsi, polaris10, ACO, DRM 3.61, 6.14.0-37-generic)",
            "peak_mean_gflops": 915.9368454249125,
            "avg_mean_gflops": 910.3623129183852,
            "p95_time_ms": 5.998835999707808,
            "max_error_max": 0.000335693359375,
            "t5_overhead_percent": 1.1359705427558824,
            "t5_false_positive_rate": 0.0,
            "t5_disable_events": 0,
            "t5_disable_reason": null
          },
          "snapshot": 4
        },
        {
          "status": "ok",
          "returncode": 0,
          "platform_selector": "Clover",
          "kernel": "auto_t5_guarded",
          "size": 2048,
          "seed": 8658,
          "metrics": {
            "platform": "Clover",
            "device": "AMD Radeon RX 590 GME (radeonsi, polaris10, ACO, DRM 3.61, 6.14.0-37-generic)",
            "peak_mean_gflops": 781.9443745359492,
            "avg_mean_gflops": 777.4836490617053,
            "p95_time_ms": 21.973668749342323,
            "max_error_max": 0.0004730224609375,
            "t5_overhead_percent": 0.5265244732914203,
            "t5_false_positive_rate": 0.0,
            "t5_disable_events": 0,
            "t5_disable_reason": null
          },
          "snapshot": 4
        }
      ],
      "evaluation": {
        "checks": {
          "all_runs_success": {
            "pass": true
          },
          "pressure_failures_zero": {
            "observed": 0,
            "required": 0,
            "pass": true
          },
          "correctness_bound_all_runs": {
            "observed_max": 0.000579833984375,
            "required_max": 0.001,
            "pass": true
          },
          "t3_guardrails_all_runs": {
            "observed_fallback_max": 0.0,
            "observed_policy_disabled_total": 0,
            "pass": true
          },
          "t5_guardrails_hard": {
            "observed_disable_total": 0,
            "observed_fp_max": 0.0,
            "observed_overhead_max": 1.1359705427558824,
            "soft_limit_percent": 3.0,
            "hard_limit_percent": 5.0,
            "pass": true
          },
          "t5_overhead_soft_limit": {
            "observed_overhead_max": 1.1359705427558824,
            "required_max": 3.0,
            "pass": true
          },
          "no_regression_vs_block6_clover": {
            "pass": true
          }
        },
        "failed_checks": [],
        "hard_failed_checks": [],
        "soft_overhead_violation": false,
        "decision": "continue",
        "regression_rows": [
          {
            "kernel": "auto_t3_controlled",
            "size": 1400,
            "throughput_delta_percent": 0.8266480612923744,
            "p95_delta_percent": -0.9400469832856417
          },
          {
            "kernel": "auto_t3_controlled",
            "size": 2048,
            "throughput_delta_percent": -0.18972361538887905,
            "p95_delta_percent": 0.0829568142029125
          },
          {
            "kernel": "auto_t5_guarded",
            "size": 1400,
            "throughput_delta_percent": 0.1093933782358902,
            "p95_delta_percent": 0.22089071956658382
          },
          {
            "kernel": "auto_t5_guarded",
            "size": 2048,
            "throughput_delta_percent": -0.06000696107528793,
            "p95_delta_percent": -0.05851119709715389
          }
        ],
        "soft_overhead_streak": 0
      }
    }
  ],
  "pressure": [
    {
      "snapshot": 1,
      "requested": 3,
      "completed": 3,
      "failures": 0,
      "errors": []
    },
    {
      "snapshot": 2,
      "requested": 3,
      "completed": 3,
      "failures": 0,
      "errors": []
    },
    {
      "snapshot": 3,
      "requested": 3,
      "completed": 3,
      "failures": 0,
      "errors": []
    },
    {
      "snapshot": 4,
      "requested": 3,
      "completed": 3,
      "failures": 0,
      "errors": []
    }
  ],
  "runs": [
    {
      "status": "ok",
      "returncode": 0,
      "platform_selector": "Clover",
      "kernel": "auto_t3_controlled",
      "size": 1400,
      "seed": 5010,
      "metrics": {
        "platform": "Clover",
        "device": "AMD Radeon RX 590 GME (radeonsi, polaris10, ACO, DRM 3.61, 6.14.0-37-generic)",
        "peak_mean_gflops": 902.514286702161,
        "avg_mean_gflops": 882.110541576449,
        "p95_time_ms": 6.107363200680993,
        "max_error_max": 0.000335693359375,
        "t3_fallback_rate": 0.0,
        "t3_policy_disabled": false
      },
      "snapshot": 1
    },
    {
      "status": "ok",
      "returncode": 0,
      "platform_selector": "Clover",
      "kernel": "auto_t3_controlled",
      "size": 2048,
      "seed": 5658,
      "metrics": {
        "platform": "Clover",
        "device": "AMD Radeon RX 590 GME (radeonsi, polaris10, ACO, DRM 3.61, 6.14.0-37-generic)",
        "peak_mean_gflops": 775.7337529068676,
        "avg_mean_gflops": 772.2442422736601,
        "p95_time_ms": 22.14883344995542,
        "max_error_max": 0.00048828125,
        "t3_fallback_rate": 0.0,
        "t3_policy_disabled": false
      },
      "snapshot": 1
    },
    {
      "status": "ok",
      "returncode": 0,
      "platform_selector": "Clover",
      "kernel": "auto_t5_guarded",
      "size": 1400,
      "seed": 5010,
      "metrics": {
        "platform": "Clover",
        "device": "AMD Radeon RX 590 GME (radeonsi, polaris10, ACO, DRM 3.61, 6.14.0-37-generic)",
        "peak_mean_gflops": 920.0366177279946,
        "avg_mean_gflops": 907.6401013710683,
        "p95_time_ms": 5.967696349489415,
        "max_error_max": 0.000335693359375,
        "t5_overhead_percent": 1.1883291079490017,
        "t5_false_positive_rate": 0.0,
        "t5_disable_events": 0,
        "t5_disable_reason": null
      },
      "snapshot": 1
    },
    {
      "status": "ok",
      "returncode": 0,
      "platform_selector": "Clover",
      "kernel": "auto_t5_guarded",
      "size": 2048,
      "seed": 5658,
      "metrics": {
        "platform": "Clover",
        "device": "AMD Radeon RX 590 GME (radeonsi, polaris10, ACO, DRM 3.61, 6.14.0-37-generic)",
        "peak_mean_gflops": 781.4818164860301,
        "avg_mean_gflops": 776.176017982146,
        "p95_time_ms": 22.00527834975219,
        "max_error_max": 0.00048828125,
        "t5_overhead_percent": 0.5391262322163354,
        "t5_false_positive_rate": 0.0,
        "t5_disable_events": 0,
        "t5_disable_reason": null
      },
      "snapshot": 1
    },
    {
      "status": "ok",
      "returncode": 0,
      "platform_selector": "Clover",
      "kernel": "auto_t3_controlled",
      "size": 1400,
      "seed": 6010,
      "metrics": {
        "platform": "Clover",
        "device": "AMD Radeon RX 590 GME (radeonsi, polaris10, ACO, DRM 3.61, 6.14.0-37-generic)",
        "peak_mean_gflops": 904.5440808209981,
        "avg_mean_gflops": 880.1362681314855,
        "p95_time_ms": 6.1243212997851515,
        "max_error_max": 0.000335693359375,
        "t3_fallback_rate": 0.0,
        "t3_policy_disabled": false
      },
      "snapshot": 2
    },
    {
      "status": "ok",
      "returncode": 0,
      "platform_selector": "Clover",
      "kernel": "auto_t3_controlled",
      "size": 2048,
      "seed": 6658,
      "metrics": {
        "platform": "Clover",
        "device": "AMD Radeon RX 590 GME (radeonsi, polaris10, ACO, DRM 3.61, 6.14.0-37-generic)",
        "peak_mean_gflops": 776.314089583971,
        "avg_mean_gflops": 771.3104908261703,
        "p95_time_ms": 22.14926699953139,
        "max_error_max": 0.0005035400390625,
        "t3_fallback_rate": 0.0,
        "t3_policy_disabled": false
      },
      "snapshot": 2
    },
    {
      "status": "ok",
      "returncode": 0,
      "platform_selector": "Clover",
      "kernel": "auto_t5_guarded",
      "size": 1400,
      "seed": 6010,
      "metrics": {
        "platform": "Clover",
        "device": "AMD Radeon RX 590 GME (radeonsi, polaris10, ACO, DRM 3.61, 6.14.0-37-generic)",
        "peak_mean_gflops": 914.4301929182327,
        "avg_mean_gflops": 905.1384547252412,
        "p95_time_ms": 6.002922700099589,
        "max_error_max": 0.000335693359375,
        "t5_overhead_percent": 1.1245681042207534,
        "t5_false_positive_rate": 0.0,
        "t5_disable_events": 0,
        "t5_disable_reason": null
      },
      "snapshot": 2
    },
    {
      "status": "ok",
      "returncode": 0,
      "platform_selector": "Clover",
      "kernel": "auto_t5_guarded",
      "size": 2048,
      "seed": 6658,
      "metrics": {
        "platform": "Clover",
        "device": "AMD Radeon RX 590 GME (radeonsi, polaris10, ACO, DRM 3.61, 6.14.0-37-generic)",
        "peak_mean_gflops": 782.198977200597,
        "avg_mean_gflops": 777.2321488138107,
        "p95_time_ms": 21.96612349998759,
        "max_error_max": 0.00048828125,
        "t5_overhead_percent": 0.5277041447846018,
        "t5_false_positive_rate": 0.0,
        "t5_disable_events": 0,
        "t5_disable_reason": null
      },
      "snapshot": 2
    },
    {
      "status": "ok",
      "returncode": 0,
      "platform_selector": "Clover",
      "kernel": "auto_t3_controlled",
      "size": 1400,
      "seed": 7010,
      "metrics": {
        "platform": "Clover",
        "device": "AMD Radeon RX 590 GME (radeonsi, polaris10, ACO, DRM 3.61, 6.14.0-37-generic)",
        "peak_mean_gflops": 899.523818446503,
        "avg_mean_gflops": 884.3712457172705,
        "p95_time_ms": 6.162586850177831,
        "max_error_max": 0.0002899169921875,
        "t3_fallback_rate": 0.0,
        "t3_policy_disabled": false
      },
      "snapshot": 3
    },
    {
      "status": "ok",
      "returncode": 0,
      "platform_selector": "Clover",
      "kernel": "auto_t3_controlled",
      "size": 2048,
      "seed": 7658,
      "metrics": {
        "platform": "Clover",
        "device": "AMD Radeon RX 590 GME (radeonsi, polaris10, ACO, DRM 3.61, 6.14.0-37-generic)",
        "peak_mean_gflops": 774.4109824945529,
        "avg_mean_gflops": 770.7606068520714,
        "p95_time_ms": 22.204869900315316,
        "max_error_max": 0.000579833984375,
        "t3_fallback_rate": 0.0,
        "t3_policy_disabled": false
      },
      "snapshot": 3
    },
    {
      "status": "ok",
      "returncode": 0,
      "platform_selector": "Clover",
      "kernel": "auto_t5_guarded",
      "size": 1400,
      "seed": 7010,
      "metrics": {
        "platform": "Clover",
        "device": "AMD Radeon RX 590 GME (radeonsi, polaris10, ACO, DRM 3.61, 6.14.0-37-generic)",
        "peak_mean_gflops": 917.2692935421951,
        "avg_mean_gflops": 898.8232798002334,
        "p95_time_ms": 5.996161849543569,
        "max_error_max": 0.0002899169921875,
        "t5_overhead_percent": 1.2053005048759495,
        "t5_false_positive_rate": 0.0,
        "t5_disable_events": 0,
        "t5_disable_reason": null
      },
      "snapshot": 3
    },
    {
      "status": "ok",
      "returncode": 0,
      "platform_selector": "Clover",
      "kernel": "auto_t5_guarded",
      "size": 2048,
      "seed": 7658,
      "metrics": {
        "platform": "Clover",
        "device": "AMD Radeon RX 590 GME (radeonsi, polaris10, ACO, DRM 3.61, 6.14.0-37-generic)",
        "peak_mean_gflops": 781.7289685383374,
        "avg_mean_gflops": 777.1847551178129,
        "p95_time_ms": 21.992245749652284,
        "max_error_max": 0.00048828125,
        "t5_overhead_percent": 0.5298428635343416,
        "t5_false_positive_rate": 0.0,
        "t5_disable_events": 0,
        "t5_disable_reason": null
      },
      "snapshot": 3
    },
    {
      "status": "ok",
      "returncode": 0,
      "platform_selector": "Clover",
      "kernel": "auto_t3_controlled",
      "size": 1400,
      "seed": 8010,
      "metrics": {
        "platform": "Clover",
        "device": "AMD Radeon RX 590 GME (radeonsi, polaris10, ACO, DRM 3.61, 6.14.0-37-generic)",
        "peak_mean_gflops": 903.5073225613546,
        "avg_mean_gflops": 882.1237006860633,
        "p95_time_ms": 6.075018699903012,
        "max_error_max": 0.00029754638671875,
        "t3_fallback_rate": 0.0,
        "t3_policy_disabled": false
      },
      "snapshot": 4
    },
    {
      "status": "ok",
      "returncode": 0,
      "platform_selector": "Clover",
      "kernel": "auto_t3_controlled",
      "size": 2048,
      "seed": 8658,
      "metrics": {
        "platform": "Clover",
        "device": "AMD Radeon RX 590 GME (radeonsi, polaris10, ACO, DRM 3.61, 6.14.0-37-generic)",
        "peak_mean_gflops": 774.6460671621267,
        "avg_mean_gflops": 771.0135509284464,
        "p95_time_ms": 22.20921195007577,
        "max_error_max": 0.000579833984375,
        "t3_fallback_rate": 0.0,
        "t3_policy_disabled": false
      },
      "snapshot": 4
    },
    {
      "status": "ok",
      "returncode": 0,
      "platform_selector": "Clover",
      "kernel": "auto_t5_guarded",
      "size": 1400,
      "seed": 8010,
      "metrics": {
        "platform": "Clover",
        "device": "AMD Radeon RX 590 GME (radeonsi, polaris10, ACO, DRM 3.61, 6.14.0-37-generic)",
        "peak_mean_gflops": 915.9368454249125,
        "avg_mean_gflops": 910.3623129183852,
        "p95_time_ms": 5.998835999707808,
        "max_error_max": 0.000335693359375,
        "t5_overhead_percent": 1.1359705427558824,
        "t5_false_positive_rate": 0.0,
        "t5_disable_events": 0,
        "t5_disable_reason": null
      },
      "snapshot": 4
    },
    {
      "status": "ok",
      "returncode": 0,
      "platform_selector": "Clover",
      "kernel": "auto_t5_guarded",
      "size": 2048,
      "seed": 8658,
      "metrics": {
        "platform": "Clover",
        "device": "AMD Radeon RX 590 GME (radeonsi, polaris10, ACO, DRM 3.61, 6.14.0-37-generic)",
        "peak_mean_gflops": 781.9443745359492,
        "avg_mean_gflops": 777.4836490617053,
        "p95_time_ms": 21.973668749342323,
        "max_error_max": 0.0004730224609375,
        "t5_overhead_percent": 0.5265244732914203,
        "t5_false_positive_rate": 0.0,
        "t5_disable_events": 0,
        "t5_disable_reason": null
      },
      "snapshot": 4
    }
  ],
  "rollback_event": null,
  "evaluation": {
    "checks": {
      "minimum_snapshots_completed": {
        "observed": 4,
        "required_min": 2,
        "pass": true
      },
      "all_snapshot_hard_checks_passed": {
        "pass": true
      },
      "soft_overhead_consecutive_below_limit": {
        "observed_max_streak": 0,
        "required_lt": 3,
        "pass": true
      },
      "rollback_policy_enforced": {
        "pass": true
      },
      "drift_abs_percent_bounded": {
        "required_abs_max": 10.0,
        "pass": true
      }
    },
    "failed_checks": [],
    "decision": "promote",
    "rationale": "Low-scope rollout passed hourly snapshots with stable guardrails and no rollback trigger.",
    "drift_rows": [
      {
        "kernel": "auto_t3_controlled",
        "size": 1400,
        "first_avg_gflops": 882.110541576449,
        "last_avg_gflops": 882.1237006860633,
        "drift_percent": 0.0014917755761997826
      },
      {
        "kernel": "auto_t3_controlled",
        "size": 2048,
        "first_avg_gflops": 772.2442422736601,
        "last_avg_gflops": 771.0135509284464,
        "drift_percent": -0.15936555792119195
      },
      {
        "kernel": "auto_t5_guarded",
        "size": 1400,
        "first_avg_gflops": 907.6401013710683,
        "last_avg_gflops": 910.3623129183852,
        "drift_percent": 0.2999219121328751
      },
      {
        "kernel": "auto_t5_guarded",
        "size": 2048,
        "first_avg_gflops": 776.176017982146,
        "last_avg_gflops": 777.4836490617053,
        "drift_percent": 0.16847094592779333
      }
    ],
    "warning_snapshots": [],
    "hard_failure_snapshots": []
  }
}
